{
	"$schema": "https://json.schemastore.org/block.json",
	"apiVersion": 2,
	"name": "lp-guti-blocks/hero",
	"version": "0.1.0",
	"title": "Hero",
	"category": "liveperson",
	"icon": "cover-image",
	"description": "Example block written with ESNext standard and JSX support – build step required.",
	"supports": {
		"html": false
	},
	"textdomain": "lp-guti-blocks",
	"editorScript": "file:../../build/all.js",
	"editorStyle": "file:../../build/all.css",
	"style": "file:../../build/style-all.css",
	"attributes": {
		"togglePadding": {
			"type": "boolean",
			"default": false
		},
		"lottieFile": {},
		"lottieId": {},
		"backgroundColor": {},
		"backgroundImage": {},
		"backgroundImageID": {},
		"logoWall": {},
		"logoWallId": {},
		"logoWallAlt": {},
		"primaryBtnText": {},
		"primaryBtnLink": {},
		"secondaryBtnText": {},
		"secondaryBtnLink": {},
		"kicker": {
			"default": "LIVEPERSON KICKER"
		},
		"header": {
			"default": "Header Text"
		},
		"subHeader": {
			"default": "Subheading."
		},
		"logoWall": {},
		"heroImage": {},
		"mediaId": {
			"default": 0,
			"type": "number"
		},
		"mediaUrl": {},
		"mediaAlt": {
			"type": "string",
			"default": "PlaceHolder"
		},
		"logoHeader": {}
	}
}
